{
  "plants": [
    {
      "id": 1,
      "name": "Aloe",
      "image": "./images/aloe.jpg",
      "price": 15.99
    },
    {
      "id": 2,
      "name": "ZZ Plant",
      "image": "./images/zz-plant.jpg",
      "price": 25.98
    },
    {
      "id": 3,
      "name": "Pilea peperomioides",
      "image": "./images/pilea.jpg",
      "price": 5.99
    },
    {
      "id": 4,
      "name": "Pothos",
      "image": "./images/pothos.jpg",
      "price": 12.11
    },
    {
      "id": 5,
      "name": "Jade",
      "image": "./images/jade.jpg",
      "price": 10.37
    },
    {
      "id": 6,
      "name": "Monstera Deliciosa",
      "image": "./images/monstera.jpg",
      "price": 25.99
    },
    {
      "id": 7,
      "name": "Fiddle Leaf Fig",
      "image": "./images/fiddle-leaf-fig.jpg",
      "price": 55
    },
    {
      "name": "adsa",
      "image": "https://media.istockphoto.com/id/479542154/photo/miso-ramen-noodles-with-egg-enoki-and-pak-choi.jpg?s=1024x1024&w=is&k=20&c=hii8gI4k6SMm35k44dGW8hNBXPPDsZ9dk6XfLlXx1OE=",
      "price": 20,
      "id": 8
    },
    {
      "name": "asdd",
      "image": "https://media.istockphoto.com/id/479542154/photo/miso-ramen-noodles-with-egg-enoki-and-pak-choi.jpg?s=1024x1024&w=is&k=20&c=hii8gI4k6SMm35k44dGW8hNBXPPDsZ9dk6XfLlXx1OE=",
      "price": 200,
      "id": 9
    },
    {
      "name": "Parker Connolly",
      "image": "https://media.istockphoto.com/id/479542154/photo/miso-ramen-noodles-with-egg-enoki-and-pak-choi.jpg?s=1024x1024&w=is&k=20&c=hii8gI4k6SMm35k44dGW8hNBXPPDsZ9dk6XfLlXx1OE=",
      "price": 123,
      "id": 10
    },
    {
      "name": "Parker Connolly",
      "image": "https://media.istockphoto.com/id/479542154/photo/miso-ramen-noodles-with-egg-enoki-and-pak-choi.jpg?s=1024x1024&w=is&k=20&c=hii8gI4k6SMm35k44dGW8hNBXPPDsZ9dk6XfLlXx1OE=",
      "price": 20,
      "id": 11
    },
    {
      "name": "Parker Connolly",
      "image": "https://media.istockphoto.com/id/479542154/photo/miso-ramen-noodles-with-egg-enoki-and-pak-choi.jpg?s=1024x1024&w=is&k=20&c=hii8gI4k6SMm35k44dGW8hNBXPPDsZ9dk6XfLlXx1OE=",
      "price": 20123,
      "id": 12
    },
    {
      "name": "Parker Connolly",
      "price": 20,
      "id": 13
    },
    {
      "name": "Parker Connolly",
      "image": "https://media.istockphoto.com/id/479542154/photo/miso-ramen-noodles-with-egg-enoki-and-pak-choi.jpg?s=1024x1024&w=is&k=20&c=hii8gI4k6SMm35k44dGW8hNBXPPDsZ9dk6XfLlXx1OE=",
      "price": 200,
      "id": 14
    },
    {
      "name": "Parker Connolly",
      "image": "https://media.istockphoto.com/id/479542154/photo/miso-ramen-noodles-with-egg-enoki-and-pak-choi.jpg?s=1024x1024&w=is&k=20&c=hii8gI4k6SMm35k44dGW8hNBXPPDsZ9dk6XfLlXx1OE=",
      "price": 2300,
      "id": 15
    }
  ]
}